bioCalc/__init__.py
bioCalc/bioCalc.py
bioCalc-1.1.2b0.dist-info/LICENSE
bioCalc-1.1.2b0.dist-info/METADATA
bioCalc-1.1.2b0.dist-info/WHEEL
bioCalc-1.1.2b0.dist-info/entry_points.txt
bioCalc-1.1.2b0.dist-info/top_level.txt
bioCalc-1.1.2b0.dist-info/RECORD
